event_routing_backends/__init__.py
event_routing_backends/apps.py
event_routing_backends/models.py
event_routing_backends/urls.py
event_routing_backends/templates/event_routing_backends/base.html
event_routing_backends-0.1.0.dist-info/LICENSE.txt
event_routing_backends-0.1.0.dist-info/METADATA
event_routing_backends-0.1.0.dist-info/WHEEL
event_routing_backends-0.1.0.dist-info/top_level.txt
event_routing_backends-0.1.0.dist-info/RECORD
