Metadata-Version: 2.1
Name: event-routing-backends
Version: 0.1.0
Summary: Various backends for receiving edX LMS events.
Home-page: https://github.com/edx/event-routing-backends
Author: edX
Author-email: oscm@edx.org
License: AGPL 3.0
Keywords: Python edx
Platform: UNKNOWN
Classifier: Development Status :: 3 - Alpha
Classifier: Framework :: Django
Classifier: Framework :: Django :: 2.2
Classifier: Framework :: Django :: 3.0
Classifier: Intended Audience :: Developers
Classifier: License :: OSI Approved :: GNU Affero General Public License v3 or later (AGPLv3+)
Classifier: Natural Language :: English
Classifier: Programming Language :: Python :: 3
Classifier: Programming Language :: Python :: 3.5
Classifier: Programming Language :: Python :: 3.8
Requires-Python: >=3.5
Requires-Dist: Django (>=1.11)
